batsoc/__init__.py
batsoc/batsoc.py
batsoc/curves/BatteryType.ALKALINE.csv
batsoc/curves/BatteryType.CR2032.csv
batsoc/curves/BatteryType.LI_ION.csv
batsoc/curves/BatteryType.NICD.csv
batsoc/tests/__init__.py
batsoc/tests/test_batsoc.py
batsoc-0.9.3.dist-info/LICENSE
batsoc-0.9.3.dist-info/METADATA
batsoc-0.9.3.dist-info/WHEEL
batsoc-0.9.3.dist-info/top_level.txt
batsoc-0.9.3.dist-info/RECORD
