Metadata-Version: 2.1
Name: batsoc
Version: 0.9.3
Summary: Library for estimating state of charge from battery cell voltage
Author-email: Matti Eiden <snaipperi@gmail.com>
License: MIT
Keywords: data,mapping
Classifier: Programming Language :: Python :: 3
Classifier: Development Status :: 3 - Alpha
Classifier: License :: OSI Approved :: MIT License
Classifier: Operating System :: OS Independent
Requires-Python: >=3.7
License-File: LICENSE
